COPYING
Cargo.toml
LICENSE
README.md
cratermaker-2025.12.2a0.dist-info/METADATA
cratermaker-2025.12.2a0.dist-info/WHEEL
cratermaker-2025.12.2a0.dist-info/licenses/COPYING
cratermaker-2025.12.2a0.dist-info/licenses/LICENSE
cratermaker.libs/libgfortran-8634ef04.so.3
cratermaker.libs/libopenblas-8966572e.so.0
cratermaker/__init__.py
cratermaker/_cratermaker.cpython-311-aarch64-linux-gnu.so
cratermaker/_version.py
cratermaker/components/counting/__init__.py
cratermaker/components/counting/minton2019.py
cratermaker/components/crater/__init__.py
cratermaker/components/morphology/__init__.py
cratermaker/components/morphology/du2025.py
cratermaker/components/morphology/simplemoon.py
cratermaker/components/production/__init__.py
cratermaker/components/production/neukum.py
cratermaker/components/production/powerlaw.py
cratermaker/components/projectile/__init__.py
cratermaker/components/projectile/asteroids.py
cratermaker/components/projectile/comets.py
cratermaker/components/projectile/generic.py
cratermaker/components/scaling/__init__.py
cratermaker/components/scaling/ctem.py
cratermaker/components/scaling/montecarlo.py
cratermaker/components/surface/__init__.py
cratermaker/components/surface/arbitrary_resolution.py
cratermaker/components/surface/datasurface.py
cratermaker/components/surface/hireslocal.py
cratermaker/components/surface/icosphere.py
cratermaker/components/target/__init__.py
cratermaker/constants.py
cratermaker/core/__init__.py
cratermaker/core/base.py
cratermaker/core/simulation.py
cratermaker/utils/__init__.py
cratermaker/utils/general_utils.py
cratermaker/utils/montecarlo_utils.py
pyproject.toml
cratermaker-2025.12.2a0.dist-info/RECORD
