Metadata-Version: 2.4
Name: cratermaker
Version: 2025.12.2a0
Classifier: Development Status :: 3 - Alpha
Classifier: Intended Audience :: Science/Research
Classifier: Topic :: Scientific/Engineering :: Astronomy
Classifier: License :: OSI Approved :: GNU General Public License v3 or later (GPLv3+)
Classifier: Programming Language :: Python :: 3
Classifier: Programming Language :: Rust
Classifier: Operating System :: MacOS
Classifier: Operating System :: POSIX :: Linux
Requires-Dist: numpy
Requires-Dist: dask>=2025.11.0
Requires-Dist: xarray>=2025.11.0
Requires-Dist: uxarray>=2025.10.0
Requires-Dist: vtk>=9.5
Requires-Dist: scipy
Requires-Dist: matplotlib
Requires-Dist: tqdm
Requires-Dist: pyogrio
Requires-Dist: trimesh
Requires-Dist: datashader>=0.18.0
Requires-Dist: geoviews>=1.14.0
Requires-Dist: pyyaml>=6
Requires-Dist: astropy>=7
Requires-Dist: pyvista
Requires-Dist: rasterio>=1.4.4
Requires-Dist: pytest ; extra == 'tests'
Requires-Dist: sphinx<9 ; extra == 'docs'
Requires-Dist: sphinx-autosummary-accessors ; extra == 'docs'
Requires-Dist: sphinx-book-theme>=0.3.0 ; extra == 'docs'
Requires-Dist: sphinx-copybutton ; extra == 'docs'
Requires-Dist: sphinx-design ; extra == 'docs'
Requires-Dist: sphinx-inline-tabs ; extra == 'docs'
Requires-Dist: sphinxext-rediraffe ; extra == 'docs'
Requires-Dist: sphinxext-opengraph ; extra == 'docs'
Requires-Dist: sphinx-gallery ; extra == 'docs'
Requires-Dist: ipython ; extra == 'docs'
Requires-Dist: ipykernel ; extra == 'docs'
Requires-Dist: ipywidgets ; extra == 'docs'
Requires-Dist: jupyter-server-proxy ; extra == 'docs'
Requires-Dist: nest-asyncio ; extra == 'docs'
Requires-Dist: trame-client>=2.12.7 ; extra == 'docs'
Requires-Dist: trame-server>=2.11.7 ; extra == 'docs'
Requires-Dist: trame-vtk>=2.5.8 ; extra == 'docs'
Requires-Dist: trame-vuetify>=2.3.1 ; extra == 'docs'
Requires-Dist: trame>=2.5.2 ; extra == 'docs'
Provides-Extra: tests
Provides-Extra: docs
License-File: LICENSE
License-File: COPYING
Keywords: astronomy,astrophysics,planetary,monte carlo,moon,landscape evolution
Author-email: "David A. Minton" <daminton@purdue.edu>
Maintainer-email: "David A. Minton" <daminton@purdue.edu>
Requires-Python: >=3.10, <3.14
Project-URL: Repository, https://github.com/MintonGroup/cratermaker
